backgroundlog/__init__.py
backgroundlog/handlers/__init__.py
backgroundlog/handlers/thread_handler.py
backgroundlog/performance/__init__.py
backgroundlog/performance/run_performance_comparison.py
backgroundlog/tests/__init__.py
backgroundlog/tests/unit/__init__.py
backgroundlog/tests/unit/test_thread_handler.py
backgroundlog/tests/unit/test_thread_handler_queue.py
backgroundlog-0.2.6.dist-info/licenses/LICENSE
backgroundlog-0.2.6.dist-info/METADATA
backgroundlog-0.2.6.dist-info/WHEEL
backgroundlog-0.2.6.dist-info/top_level.txt
backgroundlog-0.2.6.dist-info/RECORD
