Metadata-Version: 2.4
Name: backgroundlog
Version: 0.2.6
Summary: A logging handler wrapper to improve logging performace by sending writes to a background thread
Author-email: "Diego J. Romero López" <diegojromerolopez@gmail.com>
Project-URL: repository, https://github.com/diegojromerolopez/backgroundlog
Project-URL: documentation, https://github.com/diegojromerolopez/backgroundlog/blob/main/README.md
Project-URL: Bug Tracker, https://github.com/diegojromerolopez/backgroundlog/issues
Keywords: logging,log,thread,threading,non-blocking
Classifier: Programming Language :: Python :: Implementation :: CPython
Classifier: Programming Language :: Python :: Implementation :: PyPy
Classifier: Programming Language :: Python :: 3.10
Classifier: Programming Language :: Python :: 3.11
Classifier: Programming Language :: Python :: 3.12
Classifier: Programming Language :: Python :: 3.13
Classifier: Programming Language :: Python :: 3.14
Classifier: Topic :: Software Development :: Libraries
Classifier: Development Status :: 4 - Beta
Classifier: License :: OSI Approved :: MIT License
Requires-Python: >=3.10
License-File: LICENSE
Dynamic: license-file
